flowy/__init__.py
flowy/__main__.py
flowy/config.py
flowy/operations.py
flowy/proxy.py
flowy/result.py
flowy/serialization.py
flowy/tracer.py
flowy/utils.py
flowy/worker.py
flowy/local/__init__.py
flowy/local/config.py
flowy/local/decision.py
flowy/local/proxy.py
flowy/local/runner.py
flowy/swf/__init__.py
flowy/swf/client.py
flowy/swf/config.py
flowy/swf/decision.py
flowy/swf/history.py
flowy/swf/proxy.py
flowy/swf/starter.py
flowy/swf/worker.py
flowy-0.4.1.dist-info/DESCRIPTION.rst
flowy-0.4.1.dist-info/METADATA
flowy-0.4.1.dist-info/RECORD
flowy-0.4.1.dist-info/WHEEL
flowy-0.4.1.dist-info/entry_points.txt
flowy-0.4.1.dist-info/metadata.json
flowy-0.4.1.dist-info/top_level.txt
