Metadata-Version: 2.0
Name: flowy
Version: 0.4.1
Summary: A workflow modeling and execution library with gradual concurrency inference.
Home-page: https://github.com/severb/flowy
Author: Sever Banesiu
Author-email: banesiu.sever@gmail.com
License: MIT License
Keywords: distributed workflow modeling SWF
Platform: UNKNOWN
Classifier: Development Status :: 5 - Production/Stable
Classifier: Intended Audience :: Developers
Classifier: License :: OSI Approved :: MIT License
Classifier: Operating System :: OS Independent
Classifier: Topic :: Internet
Classifier: Programming Language :: Python :: 2.7
Classifier: Programming Language :: Python :: 3.4
Classifier: Programming Language :: Python :: 3.5
Requires-Dist: boto3 (==1.3.1)
Requires-Dist: lazy-object-proxy (==1.2.2)
Requires-Dist: venusian (>=1.0)
Requires-Dist: futures; python_version == "2.7"
Provides-Extra: docs
Requires-Dist: sphinx; extra == 'docs'
Requires-Dist: sphinx-rtd-theme; extra == 'docs'
Provides-Extra: trace
Requires-Dist: pygraphviz; extra == 'trace'
